{
  "fetched_at": "2026-04-15T11:18:27.438297+09:00",
  "period": {
    "from": "2026-03-16",
    "to": "2026-04-14"
  },
  "platforms": [
    "android",
    "ios"
  ],
  "funnel_total": {
    "install": 5916,
    "first_open": 5784,
    "estimate": 570,
    "ai_desc": 196,
    "ai_start": 182,
    "ai_result": 133,
    "sell_desc": 172,
    "sell_start": 55,
    "sell_contact": 37,
    "sell_complete": 17
  },
  "funnel_by_source": {
    "Organic": {
      "install": 1627,
      "first_open": 1591,
      "estimate": 223,
      "ai_desc": 79,
      "ai_start": 71,
      "ai_result": 56,
      "sell_desc": 66,
      "sell_start": 23,
      "sell_contact": 17,
      "sell_complete": 8
    },
    "Vpoint": {
      "install": 17,
      "first_open": 17,
      "estimate": 5,
      "ai_desc": 2,
      "ai_start": 2,
      "ai_result": 1,
      "sell_desc": 3,
      "sell_start": 1,
      "sell_contact": 0,
      "sell_complete": 0
    },
    "a8_int": {
      "install": 364,
      "first_open": 362,
      "estimate": 26,
      "ai_desc": 6,
      "ai_start": 5,
      "ai_result": 3,
      "sell_desc": 0,
      "sell_start": 0,
      "sell_contact": 0,
      "sell_complete": 0
    },
    "b-dash": {
      "install": 5,
      "first_open": 5,
      "estimate": 1,
      "ai_desc": 1,
      "ai_start": 1,
      "ai_result": 1,
      "sell_desc": 1,
      "sell_start": 0,
      "sell_contact": 0,
      "sell_complete": 0
    },
    "googleadwords_int": {
      "install": 2950,
      "first_open": 2871,
      "estimate": 186,
      "ai_desc": 63,
      "ai_start": 60,
      "ai_result": 42,
      "sell_desc": 53,
      "sell_start": 13,
      "sell_contact": 8,
      "sell_complete": 2
    },
    "rentracksaxf_int": {
      "install": 19,
      "first_open": 19,
      "estimate": 8,
      "ai_desc": 3,
      "ai_start": 3,
      "ai_result": 3,
      "sell_desc": 0,
      "sell_start": 0,
      "sell_contact": 0,
      "sell_complete": 0
    },
    "seedapp_int": {
      "install": 8,
      "first_open": 8,
      "estimate": 1,
      "ai_desc": 1,
      "ai_start": 1,
      "ai_result": 0,
      "sell_desc": 0,
      "sell_start": 0,
      "sell_contact": 0,
      "sell_complete": 0
    },
    "tiktokglobal_int": {
      "install": 426,
      "first_open": 412,
      "estimate": 37,
      "ai_desc": 12,
      "ai_start": 12,
      "ai_result": 8,
      "sell_desc": 10,
      "sell_start": 1,
      "sell_contact": 1,
      "sell_complete": 1
    },
    "ucarpac_contents_LP": {
      "install": 68,
      "first_open": 68,
      "estimate": 9,
      "ai_desc": 2,
      "ai_start": 2,
      "ai_result": 3,
      "sell_desc": 5,
      "sell_start": 2,
      "sell_contact": 2,
      "sell_complete": 2
    },
    "SNS": {
      "install": 0,
      "first_open": 0,
      "estimate": 0,
      "ai_desc": 0,
      "ai_start": 0,
      "ai_result": 0,
      "sell_desc": 0,
      "sell_start": 0,
      "sell_contact": 0,
      "sell_complete": 0
    },
    "Vpoint_Livels": {
      "install": 0,
      "first_open": 0,
      "estimate": 0,
      "ai_desc": 0,
      "ai_start": 0,
      "ai_result": 0,
      "sell_desc": 0,
      "sell_start": 0,
      "sell_contact": 0,
      "sell_complete": 0
    },
    "accesstrade_int": {
      "install": 11,
      "first_open": 11,
      "estimate": 1,
      "ai_desc": 0,
      "ai_start": 0,
      "ai_result": 0,
      "sell_desc": 0,
      "sell_start": 0,
      "sell_contact": 0,
      "sell_complete": 0
    },
    "smaad_int": {
      "install": 9,
      "first_open": 9,
      "estimate": 1,
      "ai_desc": 1,
      "ai_start": 0,
      "ai_result": 0,
      "sell_desc": 0,
      "sell_start": 0,
      "sell_contact": 0,
      "sell_complete": 0
    },
    "b-dash_Mail_2025": {
      "install": 2,
      "first_open": 2,
      "estimate": 0,
      "ai_desc": 0,
      "ai_start": 0,
      "ai_result": 0,
      "sell_desc": 0,
      "sell_start": 0,
      "sell_contact": 0,
      "sell_complete": 0
    },
    "livelsqdk_int": {
      "install": 1,
      "first_open": 1,
      "estimate": 0,
      "ai_desc": 0,
      "ai_start": 0,
      "ai_result": 0,
      "sell_desc": 0,
      "sell_start": 0,
      "sell_contact": 0,
      "sell_complete": 0
    },
    "LINE": {
      "install": 4,
      "first_open": 4,
      "estimate": 0,
      "ai_desc": 0,
      "ai_start": 0,
      "ai_result": 0,
      "sell_desc": 0,
      "sell_start": 0,
      "sell_contact": 0,
      "sell_complete": 0
    },
    "Apple Search Ads": {
      "install": 405,
      "first_open": 404,
      "estimate": 72,
      "ai_desc": 26,
      "ai_start": 25,
      "ai_result": 16,
      "sell_desc": 34,
      "sell_start": 15,
      "sell_contact": 9,
      "sell_complete": 4
    }
  },
  "funnel_by_source_summary": [
    {
      "name": "googleadwords_int",
      "install": 2950,
      "first_open": 2871,
      "estimate": 186,
      "ai_desc": 63,
      "ai_start": 60,
      "ai_result": 42,
      "sell_desc": 53,
      "sell_start": 13,
      "sell_contact": 8,
      "sell_complete": 2,
      "cvr_install_to_cv": 0.1,
      "cvr_install_to_estimate": 6.3
    },
    {
      "name": "Organic",
      "install": 1627,
      "first_open": 1591,
      "estimate": 223,
      "ai_desc": 79,
      "ai_start": 71,
      "ai_result": 56,
      "sell_desc": 66,
      "sell_start": 23,
      "sell_contact": 17,
      "sell_complete": 8,
      "cvr_install_to_cv": 0.5,
      "cvr_install_to_estimate": 13.7
    },
    {
      "name": "tiktokglobal_int",
      "install": 426,
      "first_open": 412,
      "estimate": 37,
      "ai_desc": 12,
      "ai_start": 12,
      "ai_result": 8,
      "sell_desc": 10,
      "sell_start": 1,
      "sell_contact": 1,
      "sell_complete": 1,
      "cvr_install_to_cv": 0.2,
      "cvr_install_to_estimate": 8.7
    },
    {
      "name": "Apple Search Ads",
      "install": 405,
      "first_open": 404,
      "estimate": 72,
      "ai_desc": 26,
      "ai_start": 25,
      "ai_result": 16,
      "sell_desc": 34,
      "sell_start": 15,
      "sell_contact": 9,
      "sell_complete": 4,
      "cvr_install_to_cv": 1.0,
      "cvr_install_to_estimate": 17.8
    },
    {
      "name": "a8_int",
      "install": 364,
      "first_open": 362,
      "estimate": 26,
      "ai_desc": 6,
      "ai_start": 5,
      "ai_result": 3,
      "sell_desc": 0,
      "sell_start": 0,
      "sell_contact": 0,
      "sell_complete": 0,
      "cvr_install_to_cv": 0.0,
      "cvr_install_to_estimate": 7.1
    },
    {
      "name": "ucarpac_contents_LP",
      "install": 68,
      "first_open": 68,
      "estimate": 9,
      "ai_desc": 2,
      "ai_start": 2,
      "ai_result": 3,
      "sell_desc": 5,
      "sell_start": 2,
      "sell_contact": 2,
      "sell_complete": 2,
      "cvr_install_to_cv": 2.9,
      "cvr_install_to_estimate": 13.2
    },
    {
      "name": "rentracksaxf_int",
      "install": 19,
      "first_open": 19,
      "estimate": 8,
      "ai_desc": 3,
      "ai_start": 3,
      "ai_result": 3,
      "sell_desc": 0,
      "sell_start": 0,
      "sell_contact": 0,
      "sell_complete": 0,
      "cvr_install_to_cv": 0.0,
      "cvr_install_to_estimate": 42.1
    },
    {
      "name": "Vpoint",
      "install": 17,
      "first_open": 17,
      "estimate": 5,
      "ai_desc": 2,
      "ai_start": 2,
      "ai_result": 1,
      "sell_desc": 3,
      "sell_start": 1,
      "sell_contact": 0,
      "sell_complete": 0,
      "cvr_install_to_cv": 0.0,
      "cvr_install_to_estimate": 29.4
    },
    {
      "name": "accesstrade_int",
      "install": 11,
      "first_open": 11,
      "estimate": 1,
      "ai_desc": 0,
      "ai_start": 0,
      "ai_result": 0,
      "sell_desc": 0,
      "sell_start": 0,
      "sell_contact": 0,
      "sell_complete": 0,
      "cvr_install_to_cv": 0.0,
      "cvr_install_to_estimate": 9.1
    },
    {
      "name": "smaad_int",
      "install": 9,
      "first_open": 9,
      "estimate": 1,
      "ai_desc": 1,
      "ai_start": 0,
      "ai_result": 0,
      "sell_desc": 0,
      "sell_start": 0,
      "sell_contact": 0,
      "sell_complete": 0,
      "cvr_install_to_cv": 0.0,
      "cvr_install_to_estimate": 11.1
    },
    {
      "name": "seedapp_int",
      "install": 8,
      "first_open": 8,
      "estimate": 1,
      "ai_desc": 1,
      "ai_start": 1,
      "ai_result": 0,
      "sell_desc": 0,
      "sell_start": 0,
      "sell_contact": 0,
      "sell_complete": 0,
      "cvr_install_to_cv": 0.0,
      "cvr_install_to_estimate": 12.5
    },
    {
      "name": "b-dash",
      "install": 5,
      "first_open": 5,
      "estimate": 1,
      "ai_desc": 1,
      "ai_start": 1,
      "ai_result": 1,
      "sell_desc": 1,
      "sell_start": 0,
      "sell_contact": 0,
      "sell_complete": 0,
      "cvr_install_to_cv": 0.0,
      "cvr_install_to_estimate": 20.0
    },
    {
      "name": "LINE",
      "install": 4,
      "first_open": 4,
      "estimate": 0,
      "ai_desc": 0,
      "ai_start": 0,
      "ai_result": 0,
      "sell_desc": 0,
      "sell_start": 0,
      "sell_contact": 0,
      "sell_complete": 0,
      "cvr_install_to_cv": 0.0,
      "cvr_install_to_estimate": 0.0
    },
    {
      "name": "b-dash_Mail_2025",
      "install": 2,
      "first_open": 2,
      "estimate": 0,
      "ai_desc": 0,
      "ai_start": 0,
      "ai_result": 0,
      "sell_desc": 0,
      "sell_start": 0,
      "sell_contact": 0,
      "sell_complete": 0,
      "cvr_install_to_cv": 0.0,
      "cvr_install_to_estimate": 0.0
    },
    {
      "name": "livelsqdk_int",
      "install": 1,
      "first_open": 1,
      "estimate": 0,
      "ai_desc": 0,
      "ai_start": 0,
      "ai_result": 0,
      "sell_desc": 0,
      "sell_start": 0,
      "sell_contact": 0,
      "sell_complete": 0,
      "cvr_install_to_cv": 0.0,
      "cvr_install_to_estimate": 0.0
    }
  ],
  "daily_funnel": {
    "2026-03-16": {
      "install": 292,
      "sessions": 907,
      "first_open": 285,
      "estimate": 2,
      "ai_desc": 2,
      "ai_start": 2,
      "ai_result": 2,
      "sell_desc": 2,
      "sell_start": 0,
      "sell_contact": 0,
      "sell_complete": 0
    },
    "2026-03-17": {
      "install": 258,
      "sessions": 772,
      "first_open": 251,
      "estimate": 2,
      "ai_desc": 2,
      "ai_start": 2,
      "ai_result": 2,
      "sell_desc": 3,
      "sell_start": 1,
      "sell_contact": 1,
      "sell_complete": 0
    },
    "2026-03-18": {
      "install": 237,
      "sessions": 753,
      "first_open": 236,
      "estimate": 1,
      "ai_desc": 1,
      "ai_start": 1,
      "ai_result": 1,
      "sell_desc": 1,
      "sell_start": 0,
      "sell_contact": 0,
      "sell_complete": 0
    },
    "2026-03-19": {
      "install": 271,
      "sessions": 773,
      "first_open": 264,
      "estimate": 1,
      "ai_desc": 1,
      "ai_start": 1,
      "ai_result": 2,
      "sell_desc": 1,
      "sell_start": 0,
      "sell_contact": 0,
      "sell_complete": 0
    },
    "2026-03-20": {
      "install": 314,
      "sessions": 957,
      "first_open": 305,
      "estimate": 2,
      "ai_desc": 1,
      "ai_start": 1,
      "ai_result": 0,
      "sell_desc": 0,
      "sell_start": 0,
      "sell_contact": 0,
      "sell_complete": 0
    },
    "2026-03-21": {
      "install": 267,
      "sessions": 818,
      "first_open": 262,
      "estimate": 3,
      "ai_desc": 1,
      "ai_start": 1,
      "ai_result": 1,
      "sell_desc": 0,
      "sell_start": 0,
      "sell_contact": 0,
      "sell_complete": 0
    },
    "2026-03-22": {
      "install": 296,
      "sessions": 914,
      "first_open": 288,
      "estimate": 1,
      "ai_desc": 0,
      "ai_start": 0,
      "ai_result": 1,
      "sell_desc": 2,
      "sell_start": 2,
      "sell_contact": 2,
      "sell_complete": 0
    },
    "2026-03-23": {
      "install": 240,
      "sessions": 653,
      "first_open": 233,
      "estimate": 0,
      "ai_desc": 0,
      "ai_start": 0,
      "ai_result": 0,
      "sell_desc": 1,
      "sell_start": 1,
      "sell_contact": 1,
      "sell_complete": 1
    },
    "2026-03-24": {
      "install": 263,
      "sessions": 668,
      "first_open": 260,
      "estimate": 3,
      "ai_desc": 1,
      "ai_start": 1,
      "ai_result": 1,
      "sell_desc": 4,
      "sell_start": 1,
      "sell_contact": 0,
      "sell_complete": 0
    },
    "2026-03-25": {
      "install": 225,
      "sessions": 595,
      "first_open": 218,
      "estimate": 2,
      "ai_desc": 0,
      "ai_start": 0,
      "ai_result": 0,
      "sell_desc": 1,
      "sell_start": 1,
      "sell_contact": 1,
      "sell_complete": 1
    },
    "2026-03-26": {
      "install": 156,
      "sessions": 469,
      "first_open": 154,
      "estimate": 2,
      "ai_desc": 0,
      "ai_start": 0,
      "ai_result": 0,
      "sell_desc": 2,
      "sell_start": 0,
      "sell_contact": 0,
      "sell_complete": 0
    },
    "2026-03-27": {
      "install": 122,
      "sessions": 373,
      "first_open": 119,
      "estimate": 2,
      "ai_desc": 1,
      "ai_start": 1,
      "ai_result": 1,
      "sell_desc": 3,
      "sell_start": 1,
      "sell_contact": 1,
      "sell_complete": 0
    },
    "2026-03-28": {
      "install": 116,
      "sessions": 283,
      "first_open": 113,
      "estimate": 1,
      "ai_desc": 0,
      "ai_start": 0,
      "ai_result": 1,
      "sell_desc": 2,
      "sell_start": 0,
      "sell_contact": 0,
      "sell_complete": 0
    },
    "2026-03-29": {
      "install": 143,
      "sessions": 385,
      "first_open": 139,
      "estimate": 1,
      "ai_desc": 0,
      "ai_start": 0,
      "ai_result": 2,
      "sell_desc": 1,
      "sell_start": 1,
      "sell_contact": 1,
      "sell_complete": 0
    },
    "2026-03-30": {
      "install": 107,
      "sessions": 328,
      "first_open": 101,
      "estimate": 1,
      "ai_desc": 1,
      "ai_start": 1,
      "ai_result": 1,
      "sell_desc": 0,
      "sell_start": 0,
      "sell_contact": 0,
      "sell_complete": 0
    },
    "2026-03-31": {
      "install": 124,
      "sessions": 336,
      "first_open": 124,
      "estimate": 0,
      "ai_desc": 0,
      "ai_start": 0,
      "ai_result": 0,
      "sell_desc": 0,
      "sell_start": 0,
      "sell_contact": 0,
      "sell_complete": 0
    },
    "2026-04-01": {
      "install": 159,
      "sessions": 433,
      "first_open": 155,
      "estimate": 2,
      "ai_desc": 1,
      "ai_start": 1,
      "ai_result": 0,
      "sell_desc": 0,
      "sell_start": 0,
      "sell_contact": 0,
      "sell_complete": 0
    },
    "2026-04-02": {
      "install": 175,
      "sessions": 411,
      "first_open": 171,
      "estimate": 0,
      "ai_desc": 0,
      "ai_start": 0,
      "ai_result": 0,
      "sell_desc": 0,
      "sell_start": 0,
      "sell_contact": 0,
      "sell_complete": 0
    },
    "2026-04-03": {
      "install": 163,
      "sessions": 402,
      "first_open": 158,
      "estimate": 1,
      "ai_desc": 1,
      "ai_start": 1,
      "ai_result": 0,
      "sell_desc": 2,
      "sell_start": 2,
      "sell_contact": 1,
      "sell_complete": 0
    },
    "2026-04-04": {
      "install": 227,
      "sessions": 511,
      "first_open": 224,
      "estimate": 1,
      "ai_desc": 0,
      "ai_start": 0,
      "ai_result": 0,
      "sell_desc": 3,
      "sell_start": 0,
      "sell_contact": 0,
      "sell_complete": 0
    },
    "2026-04-05": {
      "install": 193,
      "sessions": 450,
      "first_open": 190,
      "estimate": 4,
      "ai_desc": 1,
      "ai_start": 0,
      "ai_result": 1,
      "sell_desc": 1,
      "sell_start": 1,
      "sell_contact": 1,
      "sell_complete": 1
    },
    "2026-04-06": {
      "install": 169,
      "sessions": 445,
      "first_open": 166,
      "estimate": 6,
      "ai_desc": 5,
      "ai_start": 5,
      "ai_result": 4,
      "sell_desc": 3,
      "sell_start": 1,
      "sell_contact": 0,
      "sell_complete": 0
    },
    "2026-04-07": {
      "install": 177,
      "sessions": 434,
      "first_open": 173,
      "estimate": 3,
      "ai_desc": 1,
      "ai_start": 1,
      "ai_result": 1,
      "sell_desc": 1,
      "sell_start": 1,
      "sell_contact": 1,
      "sell_complete": 1
    },
    "2026-04-08": {
      "install": 140,
      "sessions": 306,
      "first_open": 138,
      "estimate": 3,
      "ai_desc": 0,
      "ai_start": 0,
      "ai_result": 0,
      "sell_desc": 5,
      "sell_start": 3,
      "sell_contact": 2,
      "sell_complete": 0
    },
    "2026-04-09": {
      "install": 180,
      "sessions": 484,
      "first_open": 175,
      "estimate": 2,
      "ai_desc": 2,
      "ai_start": 1,
      "ai_result": 0,
      "sell_desc": 1,
      "sell_start": 0,
      "sell_contact": 0,
      "sell_complete": 0
    },
    "2026-04-10": {
      "install": 156,
      "sessions": 411,
      "first_open": 151,
      "estimate": 47,
      "ai_desc": 13,
      "ai_start": 13,
      "ai_result": 12,
      "sell_desc": 12,
      "sell_start": 8,
      "sell_contact": 4,
      "sell_complete": 1
    },
    "2026-04-11": {
      "install": 213,
      "sessions": 523,
      "first_open": 209,
      "estimate": 147,
      "ai_desc": 46,
      "ai_start": 43,
      "ai_result": 26,
      "sell_desc": 45,
      "sell_start": 11,
      "sell_contact": 8,
      "sell_complete": 5
    },
    "2026-04-12": {
      "install": 226,
      "sessions": 597,
      "first_open": 222,
      "estimate": 148,
      "ai_desc": 50,
      "ai_start": 45,
      "ai_result": 32,
      "sell_desc": 39,
      "sell_start": 8,
      "sell_contact": 5,
      "sell_complete": 3
    },
    "2026-04-13": {
      "install": 157,
      "sessions": 335,
      "first_open": 155,
      "estimate": 91,
      "ai_desc": 33,
      "ai_start": 30,
      "ai_result": 21,
      "sell_desc": 19,
      "sell_start": 7,
      "sell_contact": 6,
      "sell_complete": 4
    },
    "2026-04-14": {
      "install": 150,
      "sessions": 379,
      "first_open": 145,
      "estimate": 91,
      "ai_desc": 32,
      "ai_start": 31,
      "ai_result": 21,
      "sell_desc": 18,
      "sell_start": 5,
      "sell_contact": 2,
      "sell_complete": 0
    }
  },
  "sub_events": {
    "コストシミュレーション／説明": 21,
    "コストシミュレーション／スタート": 17,
    "コストシミュレーション／結果": 5,
    "ダッシュボード": 794,
    "プロフィール／スタート": 3850,
    "ローン／スタート": 13,
    "ローン／結果": 3,
    "車両情報／手動／スタート": 659,
    "通常起動": 2295
  },
  "summary": {
    "total_installs": 5916,
    "total_sessions": 16105,
    "total_cv": 17,
    "overall_cvr": 0.3,
    "organic_ratio": 0.275
  },
  "insights": [
    {
      "type": "bottleneck",
      "severity": "warning",
      "message": "離脱ポイント: 初回起動→概算相場／結果 （5,784→570人、離脱90%）"
    },
    {
      "type": "bottleneck",
      "severity": "warning",
      "message": "離脱ポイント: 売却申込／説明→売却申込／スタート （172→55人、離脱68%）"
    },
    {
      "type": "bottleneck",
      "severity": "warning",
      "message": "離脱ポイント: 概算相場／結果→AI査定／説明 （570→196人、離脱66%）"
    },
    {
      "type": "ux",
      "severity": "warning",
      "message": "売却申込の説明画面で68%が離脱（説明172人→スタート55人）。説明画面の簡素化を検討"
    },
    {
      "type": "funnel",
      "severity": "warning",
      "message": "全体CVR（インストール→売却完了）: 0.3%。改善余地あり"
    },
    {
      "type": "source_quality",
      "severity": "info",
      "message": "CV率トップ: ucarpac_contents_LP（CVR 2.9%、2件/68inst）"
    },
    {
      "type": "source_quality",
      "severity": "warning",
      "message": "a8_int: 364inst→概算相場26人まで到達するがCV 0件。申込導線に課題あり"
    },
    {
      "type": "engagement",
      "severity": "info",
      "message": "概算相場到達率: rentracksaxf_int(42%) vs Apple Search Ads(18%) → ソースで大きな品質差"
    },
    {
      "type": "route",
      "severity": "info",
      "message": "売却申込説明の到達者172人中、AI査定経由133人（推定39人はAI査定スキップ）"
    },
    {
      "type": "trend",
      "severity": "warning",
      "message": "インストール 前半→後半: 3,307→2,609（-21%減少）"
    },
    {
      "type": "trend",
      "severity": "info",
      "message": "CV 前半→後半: 2→15（+650%増加）"
    },
    {
      "type": "organic",
      "severity": "info",
      "message": "Organic比率 27.5%（1,627件/5,916件）"
    }
  ]
}